esyslog/__init__.py
esyslog/choosereactor.py
esyslog/config.py
esyslog/esapi.py
esyslog/httpclient.py
esyslog/syslog_protocol.py
esyslog/syslog_server.py
esyslog-0.0.1.dist-info/DESCRIPTION.rst
esyslog-0.0.1.dist-info/eager_resources.txt
esyslog-0.0.1.dist-info/entry_points.txt
esyslog-0.0.1.dist-info/METADATA
esyslog-0.0.1.dist-info/metadata.json
esyslog-0.0.1.dist-info/RECORD
esyslog-0.0.1.dist-info/top_level.txt
esyslog-0.0.1.dist-info/WHEEL
esyslog-0.0.1.dist-info/zip-safe
